llm_cmd_py/__init__.py
llm_cmd_py/cli.py
llm_cmd_py/executor.py
llm_cmd_py/llm.py
llm_cmd_py-0.1.1.dist-info/METADATA
llm_cmd_py-0.1.1.dist-info/WHEEL
llm_cmd_py-0.1.1.dist-info/entry_points.txt
llm_cmd_py-0.1.1.dist-info/RECORD
