Metadata-Version: 2.3
Name: llm-cmd-py
Version: 0.1.1
Summary: Python CLI tool that leverages LLMs to generate and execute shell commands through natural language input
License: MIT
Author: whyparkc
Author-email: parkyymm@hotmail.com
Requires-Python: >=3.9,<4.0
Classifier: License :: OSI Approved :: MIT License
Classifier: Programming Language :: Python :: 3
Classifier: Programming Language :: Python :: 3.9
Classifier: Programming Language :: Python :: 3.10
Classifier: Programming Language :: Python :: 3.11
Classifier: Programming Language :: Python :: 3.12
Classifier: Programming Language :: Python :: 3.13
Requires-Dist: click (>=8.1.7,<9.0.0)
Requires-Dist: inquirer (>=3.1.3,<4.0.0)
Requires-Dist: openai (>=1.3.0,<2.0.0)
Requires-Dist: python-dotenv (>=1.0.0,<2.0.0)
Project-URL: Repository, https://github.com/whyparkc/llm-cmd-py
